[{"domain": ".capcut.com", "expiry": 1702306350, "httpOnly": false, "name": "msToken", "path": "/", "sameSite": "None", "secure": true, "value": "dci7Vi40S7JN9PHp8LdBP5L-iRAojfo4xC10m89Yr1knkoc9AKNQNpe3JULSyKja3EXGtO7EUEggJEGes63YKp-evcXKyDQoi8xaBwfTwzMcZjsLWZZqK1WEBsZ9ilI="}, {"domain": ".capcut.com", "expiry": 1732978349, "httpOnly": true, "name": "odin_tt", "path": "/", "sameSite": "Lax", "secure": false, "value": "6098e25778ae0a43852f198e10bf8965391fae8be3b77f7142b1a54294693c179abd7e80e98752501154260527cd30fb8ab72209c85d3f97aad463eeae48b9a1"}, {"domain": "www.capcut.com", "expiry": 1701442463, "httpOnly": false, "name": "x_logid", "path": "/", "sameSite": "Lax", "secure": false, "value": "2023120114522171C97B4308ED9FC67242"}, {"domain": ".capcut.com", "expiry": 1732978337, "httpOnly": true, "name": "store-country-code", "path": "/", "sameSite": "Lax", "secure": false, "value": "bd"}, {"domain": "www.capcut.com", "expiry": 1732978341, "httpOnly": false, "name": "user_spaces_idc", "path": "/", "sameSite": "Lax", "secure": false, "value": "{\"7304520767524537345\":\"sg1_gcp\"}"}, {"domain": "www.capcut.com", "expiry": 1701528740, "httpOnly": false, "name": "_tea_web_id", "path": "/", "sameSite": "Lax", "secure": false, "value": "7307639099694040582"}, {"domain": ".capcut.com", "expiry": 1732978337, "httpOnly": true, "name": "store-country-code-src", "path": "/", "sameSite": "Lax", "secure": false, "value": "uid"}, {"domain": ".capcut.com", "expiry": 1732978337, "httpOnly": true, "name": "store-idc", "path": "/", "sameSite": "Lax", "secure": false, "value": "maliva"}, {"domain": ".capcut.com", "expiry": 1736002337, "httpOnly": true, "name": "sid_ucp_v1", "path": "/", "sameSite": "Lax", "secure": true, "value": "1.0.0-KDBmY2NmZmI0YjlmODIzZjY2YjYwMmYzMzM3Njc2NTAzZjliYjZkM2MKIQiGiNDevJ-yr2UQoeanqwYYnKAVIAwwpZL7qgY4AUDrBxADGgZtYWxpdmEiIGJjZjM5ZmYzODk0NmE4YzY0Y2M2Mjc0YTZlNmZmNWM5"}, {"domain": ".capcut.com", "expiry": 1736002337, "httpOnly": true, "name": "uid_tt_ss", "path": "/", "sameSite": "None", "secure": true, "value": "4b3a2cbc952994107d7660a577d43b57d8de3ba09db80527c9e89aa77848bd5f"}, {"domain": ".capcut.com", "expiry": 1736002337, "httpOnly": true, "name": "sessionid_ss", "path": "/", "sameSite": "None", "secure": true, "value": "bcf39ff38946a8c64cc6274a6e6ff5c9"}, {"domain": "www.capcut.com", "httpOnly": false, "name": "CAPCUT_THEME", "path": "/", "sameSite": "Lax", "secure": false, "value": "light"}, {"domain": ".capcut.com", "expiry": 1736002337, "httpOnly": true, "name": "ssid_ucp_v1", "path": "/", "sameSite": "None", "secure": true, "value": "1.0.0-KDBmY2NmZmI0YjlmODIzZjY2YjYwMmYzMzM3Njc2NTAzZjliYjZkM2MKIQiGiNDevJ-yr2UQoeanqwYYnKAVIAwwpZL7qgY4AUDrBxADGgZtYWxpdmEiIGJjZjM5ZmYzODk0NmE4YzY0Y2M2Mjc0YTZlNmZmNWM5"}, {"domain": ".capcut.com", "expiry": 1736002337, "httpOnly": true, "name": "sessionid", "path": "/", "sameSite": "Lax", "secure": false, "value": "bcf39ff38946a8c64cc6274a6e6ff5c9"}, {"domain": ".capcut.com", "expiry": 1736002337, "httpOnly": true, "name": "sid_tt", "path": "/", "sameSite": "Lax", "secure": false, "value": "bcf39ff38946a8c64cc6274a6e6ff5c9"}, {"domain": ".capcut.com", "expiry": 1736002337, "httpOnly": true, "name": "uid_tt", "path": "/", "sameSite": "Lax", "secure": false, "value": "4b3a2cbc952994107d7660a577d43b57d8de3ba09db80527c9e89aa77848bd5f"}, {"domain": ".capcut.com", "expiry": 1706626329, "httpOnly": false, "name": "passport_csrf_token_default", "path": "/", "sameSite": "Lax", "secure": false, "value": "a0896e8b75d7ddd37abef0cff269e36a"}, {"domain": "www.capcut.com", "expiry": 1732978340, "httpOnly": false, "name": "_v2_spipe_web_id", "path": "/", "sameSite": "Lax", "secure": false, "value": "7307639105922301958"}, {"domain": ".capcut.com", "expiry": 1732546337, "httpOnly": true, "name": "sid_guard", "path": "/", "sameSite": "Lax", "secure": false, "value": "bcf39ff38946a8c64cc6274a6e6ff5c9%7C1701442337%7C34560000%7CSat%2C+04-Jan-2025+14%3A52%3A17+GMT"}, {"domain": ".capcut.com", "expiry": 1732978337, "httpOnly": true, "name": "d_ticket", "path": "/", "sameSite": "Lax", "secure": false, "value": "ee331b141ad9ceb789404482d17938ff54e57"}, {"domain": "www.capcut.com", "expiry": 1709218349, "httpOnly": false, "name": "msToken", "path": "/", "sameSite": "Lax", "secure": false, "value": "0X-GggI8mnQHAIU1DR_i4JY4OXTGF7RwQdmijCXiyVKxGXhBQ9hagM0sxOPw92hYOO0uecyLCxa7d3FrfoHw0MCUXSgwTa9VTdqlO8J4393zjDeJx_9vDjgkDz8GARQ="}, {"domain": "www.capcut.com", "expiry": 1735570328, "httpOnly": false, "name": "COOKIE_CONSENT_PROMPT_CONFIG", "path": "/", "sameSite": "Lax", "secure": false, "value": "{%22status%22:1%2C%22settings%22:{%22firstPartyAnalytics%22:true%2C%22GoogleAnalytics%22:true}%2C%22updatedTime%22:1701442328275}"}, {"domain": ".capcut.com", "expiry": 1706626329, "httpOnly": false, "name": "passport_csrf_token", "path": "/", "sameSite": "None", "secure": true, "value": "a0896e8b75d7ddd37abef0cff269e36a"}, {"domain": ".capcut.com", "expiry": 1732978340, "httpOnly": true, "name": "ttwid", "path": "/", "sameSite": "Lax", "secure": true, "value": "1|RmokwH2xL1lTfMnSnrJnv5Hh1zZeGkqvMmLp-vYY4P8|1701442340|de36062968c87f1f305cffc6b09c951fa9256d795c95b3db247aff1b8efc5889"}, {"domain": "www.capcut.com", "httpOnly": false, "name": "s_v_web_id", "path": "/", "sameSite": "Lax", "secure": false, "value": "verify_lpmqtz4j_zJoexvbD_uWV5_44BM_AEo5_57bQcIUoh7Qj"}, {"domain": "www.capcut.com", "expiry": 1736002325, "httpOnly": false, "name": "capcut_locale", "path": "/", "sameSite": "Lax", "secure": false, "value": "en"}, {"domain": "www.capcut.com", "httpOnly": false, "name": "_ut", "path": "/", "sameSite": "Strict", "secure": false, "value": "context%253DReferer%2526source%253Denter_url%2526medium%253DDirect%2526channel_from%253Dut%2526session_start_url%253Dhttps%253A%252F%252Fwww.capcut.com%252Flogin"}]